dataframeops/__init__.py
dataframeops/cache_data.pkl
dataframeops/cacher.py
dataframeops/core_utils.py
dataframeops/relay.py
dataframeops-0.1.1.dist-info/METADATA
dataframeops-0.1.1.dist-info/WHEEL
dataframeops-0.1.1.dist-info/top_level.txt
dataframeops-0.1.1.dist-info/RECORD
