Metadata-Version: 2.4
Name: dataframeops
Version: 0.1.1
Summary: A dataframe utility module with extended caching. Experimental.
Author: Jorik Carlsen
Author-email: jorikcarlsen@protonmail.com
Classifier: Programming Language :: Python :: 3
Classifier: Operating System :: OS Independent
Requires-Python: >=3.7
Requires-Dist: pandas
Requires-Dist: openpyxl
Dynamic: author
Dynamic: author-email
Dynamic: classifier
Dynamic: description
Dynamic: description-content-type
Dynamic: requires-dist
Dynamic: requires-python
Dynamic: summary
